hardware/verilog/sram_32b_w2048.v
// Created by prof. Mingu Kang @VVIP Lab in UCSD ECE department
// Please do not spread this code without permission 
module sram_32b_w2048 (CLK, D, Q, CEN, WEN, A);

  input  CLK;
  input  WEN;//CEN(chip enable) = 0 means chip turned on//CEN = 0 WEN = 0 -> write mode
  //WEN = 1 && CEN = 0 -> read mode  //WEN = X && CEN = 1 -> (DC)chip turned off
  input  CEN;
  input  [31:0] D;
  input  [10:0] A;
  output [31:0] Q;
  parameter num = 2048;

  reg [31:0] memory [num-1:0];
  reg [10:0] add_q;
  assign Q = memory[add_q];

  always @ (posedge CLK) begin

   if (!CEN && WEN) // read  //read from this SRAM
      add_q <= A;
   if (!CEN && !WEN) // write  //write into this SRAM
      memory[A] <= D; 

  end

endmodule

hardware/verilog/core.v
module core #(
    parameter bw = 4,
    parameter psum_bw = 16,
    parameter col = 8,
    parameter row = 8
) (
    input                       clk,
    input                       reset,
    input   [bw*row-1:0]        D_xmem,
    input   [33:0]              inst,
    output                      ofifo_valid,
    output                      l0_ready,
    output                      ififo_ready,
    output  [psum_bw*col-1:0]   sfp_out
);
wire [31:0] Q1;
sram_32b_w2048 #(
) sram_xmem (
    .CLK(clk),
    .D(D_xmem),
    .A(inst[17:7]),
    .CEN(inst[19]),
    .WEN(inst[18]),
    .Q(Q1)
);

endmodule

hardware/verilog/core_tb.v
// Created by prof. Mingu Kang @VVIP Lab in UCSD ECE department
// Please do not spread this code without permission 
`timescale 1ns/1ps

module core_tb;

parameter bw = 4;
parameter psum_bw = 16;
parameter len_kij = 9;
parameter len_onij = 16;
parameter col = 8;
parameter row = 8;
parameter len_nij = 5;

reg clk = 0;
reg reset = 1;

wire [33:0] inst_q; 

reg [1:0]  inst_w_q = 0; 
reg [bw*row-1:0] D_xmem_q = 0;
reg CEN_xmem = 1;
reg WEN_xmem = 1;
reg [10:0] A_xmem = 0;
reg CEN_xmem_q = 1;
reg WEN_xmem_q = 1;
reg [10:0] A_xmem_q = 0;
reg CEN_pmem = 1;
reg WEN_pmem = 1;
reg [10:0] A_pmem = 0;
reg CEN_pmem_q = 1;
reg WEN_pmem_q = 1;
reg [10:0] A_pmem_q = 0;
reg ofifo_rd_q = 0;
reg ififo_wr_q = 0;
reg ififo_rd_q = 0;
reg l0_rd_q = 0;
reg l0_wr_q = 0;
reg execute_q = 0;
reg load_q = 0;
reg acc_q = 0;
reg acc = 0;

reg [1:0]  inst_w; 
reg [bw*row-1:0] D_xmem;
reg [psum_bw*col-1:0] answer;


reg ofifo_rd;
reg ififo_wr;
reg ififo_rd;
reg l0_rd;
reg l0_wr;
reg execute;
reg load;
reg [8*30:1] stringvar;
reg [8*30:1] w_file_name;
wire ofifo_valid;
wire [col*psum_bw-1:0] sfp_out;

integer x_file, x_scan_file ; // file_handler
integer w_file, w_scan_file ; // file_handler
integer acc_file, acc_scan_file ; // file_handler
integer out_file, out_scan_file ; // file_handler
integer captured_data; 
integer t, i, j, k, kij;
integer error;

assign inst_q[33] = acc_q;
assign inst_q[32] = CEN_pmem_q;
assign inst_q[31] = WEN_pmem_q;
assign inst_q[30:20] = A_pmem_q;
assign inst_q[19]   = CEN_xmem_q;
assign inst_q[18]   = WEN_xmem_q;
assign inst_q[17:7] = A_xmem_q;
assign inst_q[6]   = ofifo_rd_q;
assign inst_q[5]   = ififo_wr_q;
assign inst_q[4]   = ififo_rd_q;
assign inst_q[3]   = l0_rd_q;
assign inst_q[2]   = l0_wr_q;
assign inst_q[1]   = execute_q; 
assign inst_q[0]   = load_q; 


core  #(.bw(bw), .col(col), .row(row)) core_instance (
	.clk(clk), 
	.inst(inst_q),
	.ofifo_valid(ofifo_valid),
        .D_xmem(D_xmem_q), 
        .sfp_out(sfp_out), 
	.reset(reset)); 
  // corelet #(.bw(bw), .col(col), .row(row)) corelet_instance (
  //       .clk(clk),    
  //       .inst(inst_q),
  //       .ofifo_valid(ofifo_valid),
  //       .D_xmem(D_xmem_q),
  //       .sfp_out(sfp_out),
  //       .reset(reset));
  // );

initial begin 

  inst_w   = 0; 
  D_xmem   = 0;
  CEN_xmem = 1;
  WEN_xmem = 1;
  A_xmem   = 0;
  ofifo_rd = 0;
  ififo_wr = 0;
  ififo_rd = 0;
  l0_rd    = 0;
  l0_wr    = 0;
  execute  = 0;
  load     = 0;

  $dumpfile("core_tb.vcd");
  $dumpvars(0,core_tb);

  x_file = $fopen("./data/activation.txt", "r");
  // Following three lines are to remove the first three comment lines of the file
  x_scan_file = $fscanf(x_file,"%s", captured_data);
  x_scan_file = $fscanf(x_file,"%s", captured_data);
  x_scan_file = $fscanf(x_file,"%s", captured_data);

  //////// Reset /////////
  #0.5 clk = 1'b0;   reset = 1;
  #0.5 clk = 1'b1; 

  for (i=0; i<10 ; i=i+1) begin
    #0.5 clk = 1'b0;
    #0.5 clk = 1'b1;  
  end

  #0.5 clk = 1'b0;   reset = 0;
  #0.5 clk = 1'b1; 

  #0.5 clk = 1'b0;   
  #0.5 clk = 1'b1;   
  /////////////////////////

  /////// Activation data writing to memory ///////done
  for (t=0; t<len_nij; t=t+1) begin  
    #0.5 clk = 1'b0;  x_scan_file = $fscanf(x_file,"%32b", D_xmem); WEN_xmem = 0; CEN_xmem = 0; if (t>0) A_xmem = A_xmem + 1;
    #0.5 clk = 1'b1;   
  end

  #0.5 clk = 1'b0;  WEN_xmem = 1;  CEN_xmem = 1; A_xmem = 0;
  #0.5 clk = 1'b1; 

  $fclose(x_file);
  /////////////////////////////////////////////////


  for (kij=0; kij<1; kij=kij+1) begin  // kij loop

    case(kij)
     0: w_file_name = "./data/weight.txt";
    endcase
    

    w_file = $fopen(w_file_name, "r");
    // Following three lines are to remove the first three comment lines of the file
    w_scan_file = $fscanf(w_file,"%s", captured_data);
    w_scan_file = $fscanf(w_file,"%s", captured_data);
    w_scan_file = $fscanf(w_file,"%s", captured_data);

    #0.5 clk = 1'b0;   reset = 1;
    #0.5 clk = 1'b1; 

    for (i=0; i<10 ; i=i+1) begin
      #0.5 clk = 1'b0;
      #0.5 clk = 1'b1;  
    end

    #0.5 clk = 1'b0;   reset = 0;
    #0.5 clk = 1'b1; 

    #0.5 clk = 1'b0;   
    #0.5 clk = 1'b1;   





    /////// Kernel data writing to memory ///////done

    A_xmem = 11'b10000000000;

    for (t=0; t<col; t=t+1) begin  
      #0.5 clk = 1'b0;  w_scan_file = $fscanf(w_file,"%32b", D_xmem); WEN_xmem = 0; CEN_xmem = 0; if (t>0) A_xmem = A_xmem + 1; 
      #0.5 clk = 1'b1;  
    end

    #0.5 clk = 1'b0;  WEN_xmem = 1;  CEN_xmem = 1; A_xmem = 0;
    #0.5 clk = 1'b1; 
    /////////////////////////////////////
     

    /////// Kernel data writing to L0 ///////
    //...
    /////////////////////////////////////
    CEN_xmem = 0;
    WEN_xmem = 1;
    for (i=0; i<10 ; i=i+1) begin
      #0.5 clk = 1'b0;
      #0.5 clk = 1'b1;  
      A_xmem += 1;
    end
    



    /////// Kernel loading to PEs ///////
    //...
    /////////////////////////////////////
  


    ////// provide some intermission to clear up the kernel loading ///
    #0.5 clk = 1'b0;  load = 0; l0_rd = 0;
    #0.5 clk = 1'b1;  
  

    for (i=0; i<10 ; i=i+1) begin
      #0.5 clk = 1'b0;
      #0.5 clk = 1'b1;  
    end
    /////////////////////////////////////



    /////// Activation data writing to L0 ///////
    //...
    /////////////////////////////////////
    A_xmem =  11'b10000000000;
    for (i=0; i<10 ; i=i+1) begin
      #0.5 clk = 1'b0;
      #0.5 clk = 1'b1;  
      A_xmem += 1;
    end


    /////// Execution ///////
    //...
    /////////////////////////////////////



    //////// OFIFO READ ////////
    // Ideally, OFIFO should be read while execution, but we have enough ofifo
    // depth so we can fetch out after execution.
    //...
    /////////////////////////////////////


  end  // end of kij loop


  ////////// Accumulation /////////
//   out_file = $fopen("out.txt", "r");  

//   // Following three lines are to remove the first three comment lines of the file
//   out_scan_file = $fscanf(out_file,"%s", answer); 
//   out_scan_file = $fscanf(out_file,"%s", answer); 
//   out_scan_file = $fscanf(out_file,"%s", answer); 

//   error = 0;



//   $display("############ Verification Start during accumulation #############"); 

//   for (i=0; i<len_onij+1; i=i+1) begin 

//     #0.5 clk = 1'b0; 
//     #0.5 clk = 1'b1; 

//     if (i>0) begin
//      out_scan_file = $fscanf(out_file,"%128b", answer); // reading from out file to answer
//        if (sfp_out == answer)
//          $display("%2d-th output featuremap Data matched! :D", i); 
//        else begin
//          $display("%2d-th output featuremap Data ERROR!!", i); 
//          $display("sfpout: %128b", sfp_out);
//          $display("answer: %128b", answer);
//          error = 1;
//        end
//     end
   
 
//     #0.5 clk = 1'b0; reset = 1;
//     #0.5 clk = 1'b1;  
//     #0.5 clk = 1'b0; reset = 0; 
//     #0.5 clk = 1'b1;  

//     for (j=0; j<len_kij+1; j=j+1) begin 

//       #0.5 clk = 1'b0;   
//         if (j<len_kij) begin CEN_pmem = 0; WEN_pmem = 1; acc_scan_file = $fscanf(acc_file,"%11b", A_pmem); end
//                        else  begin CEN_pmem = 1; WEN_pmem = 1; end

//         if (j>0)  acc = 1;  
//       #0.5 clk = 1'b1;   
//     end

//     #0.5 clk = 1'b0; acc = 0;
//     #0.5 clk = 1'b1; 
//   end


//   if (error == 0) begin
//   	$display("############ No error detected ##############"); 
//   	$display("########### Project Completed !! ############"); 

//   end

//   $fclose(acc_file);
//   //////////////////////////////////

//   for (t=0; t<10; t=t+1) begin  
//     #0.5 clk = 1'b0;  
//     #0.5 clk = 1'b1;  
//   end

//   #10 $finish;

end

always @ (posedge clk) begin
   inst_w_q   <= inst_w; 
   D_xmem_q   <= D_xmem;
   CEN_xmem_q <= CEN_xmem;
   WEN_xmem_q <= WEN_xmem;
   A_pmem_q   <= A_pmem;
   CEN_pmem_q <= CEN_pmem;
   WEN_pmem_q <= WEN_pmem;
   A_xmem_q   <= A_xmem;
   ofifo_rd_q <= ofifo_rd;
   acc_q      <= acc;
   ififo_wr_q <= ififo_wr;
   ififo_rd_q <= ififo_rd;
   l0_rd_q    <= l0_rd;
   l0_wr_q    <= l0_wr ;
   execute_q  <= execute;
   load_q     <= load;
end


endmodule

hardware/core_tb.vcd
$date
	Sat Nov 30 18:00:42 2024
$end
$version
	Icarus Verilog
$end
$timescale
	1ps
$end
$scope module core_tb $end
$var wire 1 ! ofifo_valid $end
$var wire 128 " sfp_out [127:0] $end
$var wire 34 # inst_q [33:0] $end
$var parameter 32 $ bw $end
$var parameter 32 % col $end
$var parameter 32 & len_kij $end
$var parameter 32 ' len_nij $end
$var parameter 32 ( len_onij $end
$var parameter 32 ) psum_bw $end
$var parameter 32 * row $end
$var reg 11 + A_pmem [10:0] $end
$var reg 11 , A_pmem_q [10:0] $end
$var reg 11 - A_xmem [10:0] $end
$var reg 11 . A_xmem_q [10:0] $end
$var reg 1 / CEN_pmem $end
$var reg 1 0 CEN_pmem_q $end
$var reg 1 1 CEN_xmem $end
$var reg 1 2 CEN_xmem_q $end
$var reg 32 3 D_xmem [31:0] $end
$var reg 32 4 D_xmem_q [31:0] $end
$var reg 1 5 WEN_pmem $end
$var reg 1 6 WEN_pmem_q $end
$var reg 1 7 WEN_xmem $end
$var reg 1 8 WEN_xmem_q $end
$var reg 1 9 acc $end
$var reg 1 : acc_q $end
$var reg 1 ; clk $end
$var reg 1 < execute $end
$var reg 1 = execute_q $end
$var reg 1 > ififo_rd $end
$var reg 1 ? ififo_rd_q $end
$var reg 1 @ ififo_wr $end
$var reg 1 A ififo_wr_q $end
$var reg 2 B inst_w [1:0] $end
$var reg 2 C inst_w_q [1:0] $end
$var reg 1 D l0_rd $end
$var reg 1 E l0_rd_q $end
$var reg 1 F l0_wr $end
$var reg 1 G l0_wr_q $end
$var reg 1 H load $end
$var reg 1 I load_q $end
$var reg 1 J ofifo_rd $end
$var reg 1 K ofifo_rd_q $end
$var reg 1 L reset $end
$var reg 240 M w_file_name [240:1] $end
$var integer 32 N captured_data [31:0] $end
$var integer 32 O i [31:0] $end
$var integer 32 P kij [31:0] $end
$var integer 32 Q t [31:0] $end
$var integer 32 R w_file [31:0] $end
$var integer 32 S w_scan_file [31:0] $end
$var integer 32 T x_file [31:0] $end
$var integer 32 U x_scan_file [31:0] $end
$scope module core_instance $end
$var wire 32 V D_xmem [31:0] $end
$var wire 1 ; clk $end
$var wire 1 W ififo_ready $end
$var wire 34 X inst [33:0] $end
$var wire 1 Y l0_ready $end
$var wire 1 ! ofifo_valid $end
$var wire 1 L reset $end
$var wire 128 Z sfp_out [127:0] $end
$var wire 32 [ Q1 [31:0] $end
$var parameter 32 \ bw $end
$var parameter 32 ] col $end
$var parameter 32 ^ psum_bw $end
$var parameter 32 _ row $end
$scope module sram_xmem $end
$var wire 11 ` A [10:0] $end
$var wire 1 a CEN $end
$var wire 1 ; CLK $end
$var wire 32 b D [31:0] $end
$var wire 32 c Q [31:0] $end
$var wire 1 d WEN $end
$var parameter 32 e num $end
$var reg 11 f add_q [10:0] $end
$upscope $end
$upscope $end
$upscope $end
$enddefinitions $end
$comment Show the parameter values. $end
$dumpall
b100000000000 e
b1000 _
b10000 ^
b1000 ]
b100 \
b1000 *
b10000 )
b10000 (
b101 '
b1001 &
b1000 %
b100 $
$end
#0
$dumpvars
bx f
1d
bx c
b0 b
1a
b0 `
bx [
bz Z
zY
b110000000000011000000000000000000 X
zW
b0 V
b1 U
b10000000000000000000000000000011 T
bx S
bx R
bx Q
bx P
bx O
b101110001011100010111000100011 N
bx M
1L
0K
0J
0I
0H
0G
0F
0E
0D
b0 C
b0 B
0A
0@
0?
0>
0=
0<
0;
0:
09
18
17
16
15
b0 4
b0 3
12
11
10
1/
b0 .
b0 -
b0 ,
b0 +
b110000000000011000000000000000000 #
bz "
z!
$end
#1000
b0 O
1;
#1500
0;
#2000
b1 O
1;
#2500
0;
#3000
b10 O
1;
#3500
0;
#4000
b11 O
1;
#4500
0;
#5000
b100 O
1;
#5500
0;
#6000
b101 O
1;
#6500
0;
#7000
b110 O
1;
#7500
0;
#8000
b111 O
1;
#8500
0;
#9000
b1000 O
1;
#9500
0;
#10000
b1001 O
1;
#10500
0;
#11000
b1010 O
1;
#11500
0L
0;
#12000
1;
#12500
0;
#13000
b0 Q
1;
#13500
01
07
b100000000000010000000000000000 3
0;
#14000
0d
0a
08
b110000000000000000000000000000000 #
b110000000000000000000000000000000 X
02
b100000000000010000000000000000 4
b100000000000010000000000000000 V
b100000000000010000000000000000 b
b1 Q
1;
#14500
b1 -
b100000000000000000000000000000 3
0;
#15000
b1 `
b110000000000000000000000010000000 #
b110000000000000000000000010000000 X
b1 .
b100000000000000000000000000000 4
b100000000000000000000000000000 V
b100000000000000000000000000000 b
b10 Q
1;
#15500
b10 -
b100000000000010000000000000100 3
0;
#16000
b10 `
b110000000000000000000000100000000 #
b110000000000000000000000100000000 X
b10 .
b100000000000010000000000000100 4
b100000000000010000000000000100 V
b100000000000010000000000000100 b
b11 Q
1;
#16500
b11 -
b10 3
0;
#17000
b11 `
b110000000000000000000000110000000 #
b110000000000000000000000110000000 X
b11 .
b10 4
b10 V
b10 b
b100 Q
1;
#17500
b100 -
b1 3
0;
#18000
b100 `
b110000000000000000000001000000000 #
b110000000000000000000001000000000 X
b100 .
b1 4
b1 V
b1 b
b101 Q
1;
#18500
b0 -
11
17
0;
#19000
b0 `
1d
1a
b0 .
18
b110000000000011000000000000000000 #
b110000000000011000000000000000000 X
12
b1 S
b101110001011100010111000100011 N
b10000000000000000000000000000011 R
b10111000101111011001000110000101110100011000010010111101110111011001010110100101100111011010000111010000101110011101000111100001110100 M
b0 P
1;
#19500
1L
0;
#20000
b0 O
1;
#20500
0;
#21000
b1 O
1;
#21500
0;
#22000
b10 O
1;
#22500
0;
#23000
b11 O
1;
#23500
0;
#24000
b100 O
1;
#24500
0;
#25000
b101 O
1;
#25500
0;
#26000
b110 O
1;
#26500
0;
#27000
b111 O
1;
#27500
0;
#28000
b1000 O
1;
#28500
0;
#29000
b1001 O
1;
#29500
0;
#30000
b1010 O
1;
#30500
0L
0;
#31000
1;
#31500
0;
#32000
b10000000000 `
b110000000000011100000000000000000 #
b110000000000011100000000000000000 X
b10000000000 .
b0 Q
b10000000000 -
1;
#32500
01
07
b11110001111000000001000111111110 3
0;
#33000
0d
0a
08
b110000000000000100000000000000000 #
b110000000000000100000000000000000 X
02
b11110001111000000001000111111110 4
b11110001111000000001000111111110 V
b11110001111000000001000111111110 b
b1 Q
1;
#33500
b10000000001 -
b10010111100000001000100010000 3
0;
#34000
b10000000001 `
b110000000000000100000000010000000 #
b110000000000000100000000010000000 X
b10000000001 .
b10010111100000001000100010000 4
b10010111100000001000100010000 V
b10010111100000001000100010000 b
b10 Q
1;
#34500
b10000000010 -
b11101100000000010000001100000001 3
0;
#35000
b10000000010 `
b110000000000000100000000100000000 #
b110000000000000100000000100000000 X
b10000000010 .
b11101100000000010000001100000001 4
b11101100000000010000001100000001 V
b11101100000000010000001100000001 b
b11 Q
1;
#35500
b10000000011 -
b100000011110000000011111111 3
0;
#36000
b10000000011 `
b110000000000000100000000110000000 #
b110000000000000100000000110000000 X
b10000000011 .
b100000011110000000011111111 4
b100000011110000000011111111 V
b100000011110000000011111111 b
b100 Q
1;
#36500
b10000000100 -
b101111001100010010000100000011 3
0;
#37000
b10000000100 `
b110000000000000100000001000000000 #
b110000000000000100000001000000000 X
b10000000100 .
b101111001100010010000100000011 4
b101111001100010010000100000011 V
b101111001100010010000100000011 b
b101 Q
1;
#37500
b10000000101 -
b10001000011011111111100000010 3
0;
#38000
b10000000101 `
b110000000000000100000001010000000 #
b110000000000000100000001010000000 X
b10000000101 .
b10001000011011111111100000010 4
b10001000011011111111100000010 V
b10001000011011111111100000010 b
b110 Q
1;
#38500
b10000000110 -
b11100001110000011111111100011111 3
0;
#39000
b10000000110 `
b110000000000000100000001100000000 #
b110000000000000100000001100000000 X
b10000000110 .
b11100001110000011111111100011111 4
b11100001110000011111111100011111 V
b11100001110000011111111100011111 b
b111 Q
1;
#39500
b10000000111 -
b10000000111011001110111000100001 3
0;
#40000
b10000000111 `
b110000000000000100000001110000000 #
b110000000000000100000001110000000 X
b10000000111 .
b10000000111011001110111000100001 4
b10000000111011001110111000100001 V
b10000000111011001110111000100001 b
b1000 Q
1;
#40500
b0 -
11
17
0;
#41000
b0 `
1d
b0 .
b110000000000001000000000000000000 #
b110000000000001000000000000000000 X
18
b0 O
01
1;
#41500
0;
#42000
b1 `
b110000000000001000000000010000000 #
b110000000000001000000000010000000 X
b1 .
b100000000000010000000000000000 [
b100000000000010000000000000000 c
b0 f
b1 O
b1 -
1;
#42500
0;
#43000
b10 `
b100000000000000000000000000000 [
b100000000000000000000000000000 c
b1 f
b110000000000001000000000100000000 #
b110000000000001000000000100000000 X
b10 .
b10 O
b10 -
1;
#43500
0;
#44000
b11 `
b110000000000001000000000110000000 #
b110000000000001000000000110000000 X
b11 .
b100000000000010000000000000100 [
b100000000000010000000000000100 c
b10 f
b11 O
b11 -
1;
#44500
0;
#45000
b100 `
b10 [
b10 c
b11 f
b110000000000001000000001000000000 #
b110000000000001000000001000000000 X
b100 .
b100 O
b100 -
1;
#45500
0;
#46000
b101 `
b110000000000001000000001010000000 #
b110000000000001000000001010000000 X
b101 .
b1 [
b1 c
b100 f
b101 O
b101 -
1;
#46500
0;
#47000
b110 `
bx [
bx c
b101 f
b110000000000001000000001100000000 #
b110000000000001000000001100000000 X
b110 .
b110 O
b110 -
1;
#47500
0;
#48000
b111 `
b110000000000001000000001110000000 #
b110000000000001000000001110000000 X
b111 .
b110 f
b111 O
b111 -
1;
#48500
0;
#49000
b1000 `
b111 f
b110000000000001000000010000000000 #
b110000000000001000000010000000000 X
b1000 .
b1000 O
b1000 -
1;
#49500
0;
#50000
b1001 `
b110000000000001000000010010000000 #
b110000000000001000000010010000000 X
b1001 .
b1000 f
b1001 O
b1001 -
1;
#50500
0;
#51000
b1010 `
b1001 f
b110000000000001000000010100000000 #
b110000000000001000000010100000000 X
b1010 .
b1010 O
b1010 -
1;
#51500
0;
#52000
b1010 f
b0 O
1;
#52500
0;
#53000
b1 O
1;
#53500
0;
#54000
b10 O
1;
#54500
0;
#55000
b11 O
1;
#55500
0;
#56000
b100 O
1;
#56500
0;
#57000
b101 O
1;
#57500
0;
#58000
b110 O
1;
#58500
0;
#59000
b111 O
1;
#59500
0;
#60000
b1000 O
1;
#60500
0;
#61000
b1001 O
1;
#61500
0;
#62000
b10000000000 `
b110000000000001100000000000000000 #
b110000000000001100000000000000000 X
b10000000000 .
b10000000000 -
b0 O
1;
#62500
0;
#63000
b10000000001 `
b11110001111000000001000111111110 [
b11110001111000000001000111111110 c
b10000000000 f
b110000000000001100000000010000000 #
b110000000000001100000000010000000 X
b10000000001 .
b1 O
b10000000001 -
1;
#63500
0;
#64000
b10000000010 `
b110000000000001100000000100000000 #
b110000000000001100000000100000000 X
b10000000010 .
b10010111100000001000100010000 [
b10010111100000001000100010000 c
b10000000001 f
b10 O
b10000000010 -
1;
#64500
0;
#65000
b10000000011 `
b11101100000000010000001100000001 [
b11101100000000010000001100000001 c
b10000000010 f
b110000000000001100000000110000000 #
b110000000000001100000000110000000 X
b10000000011 .
b11 O
b10000000011 -
1;
#65500
0;
#66000
b10000000100 `
b110000000000001100000001000000000 #
b110000000000001100000001000000000 X
b10000000100 .
b100000011110000000011111111 [
b100000011110000000011111111 c
b10000000011 f
b100 O
b10000000100 -
1;
#66500
0;
#67000
b10000000101 `
b101111001100010010000100000011 [
b101111001100010010000100000011 c
b10000000100 f
b110000000000001100000001010000000 #
b110000000000001100000001010000000 X
b10000000101 .
b101 O
b10000000101 -
1;
#67500
0;
#68000
b10000000110 `
b110000000000001100000001100000000 #
b110000000000001100000001100000000 X
b10000000110 .
b10001000011011111111100000010 [
b10001000011011111111100000010 c
b10000000101 f
b110 O
b10000000110 -
1;
#68500
0;
#69000
b10000000111 `
b11100001110000011111111100011111 [
b11100001110000011111111100011111 c
b10000000110 f
b110000000000001100000001110000000 #
b110000000000001100000001110000000 X
b10000000111 .
b111 O
b10000000111 -
1;
#69500
0;
#70000
b10000001000 `
b110000000000001100000010000000000 #
b110000000000001100000010000000000 X
b10000001000 .
b10000000111011001110111000100001 [
b10000000111011001110111000100001 c
b10000000111 f
b1000 O
b10000001000 -
1;
#70500
0;
#71000
b10000001001 `
bx [
bx c
b10000001000 f
b110000000000001100000010010000000 #
b110000000000001100000010010000000 X
b10000001001 .
b1001 O
b10000001001 -
1;
#71500
0;
#72000
b10000001010 `
b110000000000001100000010100000000 #
b110000000000001100000010100000000 X
b10000001010 .
b10000001001 f
b1 P
b1010 O
b10000001010 -
1;
